blivedm/__init__.py
blivedm/client.py
blivedm/handlers.py
blivedm/models.py
blivedm-0.1.1.dist-info/LICENSE
blivedm-0.1.1.dist-info/METADATA
blivedm-0.1.1.dist-info/WHEEL
blivedm-0.1.1.dist-info/RECORD
