Metadata-Version: 2.1
Name: blivedm
Version: 0.1.1
Summary: Python获取bilibili直播弹幕的库，使用WebSocket协议
Author: xfgryujk
Requires-Python: >=3.8,<4.0
Classifier: Programming Language :: Python :: 3
Classifier: Programming Language :: Python :: 3.8
Classifier: Programming Language :: Python :: 3.9
Classifier: Programming Language :: Python :: 3.10
Classifier: Programming Language :: Python :: 3.11
Requires-Dist: aiohttp (>=3.7.4)
Requires-Dist: brotli (==1.0.9)
